ormdantic/__init__.py
ormdantic/orm.py
ormdantic/py.typed
ormdantic/generator/__init__.py
ormdantic/generator/_crud.py
ormdantic/generator/_field.py
ormdantic/generator/_lazy.py
ormdantic/generator/_query.py
ormdantic/generator/_serializer.py
ormdantic/generator/_table.py
ormdantic/handler/__init__.py
ormdantic/handler/errors.py
ormdantic/handler/helper.py
ormdantic/handler/random.py
ormdantic/handler/snake.py
ormdantic/models/__init__.py
ormdantic/models/models.py
ormdantic/types/__init__.py
ormdantic/types/base.py
ormdantic-1.7.0.dist-info/METADATA
ormdantic-1.7.0.dist-info/WHEEL
ormdantic-1.7.0.dist-info/licenses/LICENSE
ormdantic-1.7.0.dist-info/RECORD
