Metadata-Version: 2.3
Name: ormdantic
Version: 1.7.0
Summary: asynchronous ORM that uses pydantic models to represent database tables
Project-URL: Homepage, https://github.com/yezz123/ormdantic
Project-URL: Documentation, https://ormdantic.yezz.me/
Project-URL: Funding, https://github.com/sponsors/yezz123
Author-email: Yasser Tahiri <hello@yezz.me>
License-Expression: MIT
License-File: LICENSE
Keywords: asyncio,orm,pydantic,sqlalchemy
Classifier: Development Status :: 5 - Production/Stable
Classifier: Framework :: AsyncIO
Classifier: Framework :: Pydantic
Classifier: Framework :: Pydantic :: 1
Classifier: Intended Audience :: Developers
Classifier: Intended Audience :: Information Technology
Classifier: License :: OSI Approved :: MIT License
Classifier: Operating System :: OS Independent
Classifier: Programming Language :: Python
Classifier: Programming Language :: Python :: 3 :: Only
Classifier: Programming Language :: Python :: 3.10
Classifier: Programming Language :: Python :: 3.11
Classifier: Programming Language :: Python :: 3.12
Classifier: Topic :: Database
Classifier: Topic :: Internet :: WWW/HTTP :: Session
Classifier: Typing :: Typed
Requires-Python: >=3.10
Requires-Dist: pydantic!=1.7,!=1.7.1,!=1.7.2,!=1.7.3,!=1.8,!=1.8.1,<2.0.0,>=1.6.2
Requires-Dist: pypika==0.48.9
Requires-Dist: sqlalchemy[asyncio]>=2.0.0
Provides-Extra: postgresql
Requires-Dist: asyncpg; extra == 'postgresql'
Requires-Dist: psycopg2-binary; extra == 'postgresql'
Provides-Extra: sqlite
Requires-Dist: aiosqlite; extra == 'sqlite'
